mlflow_sysmetrics/__init__.py
mlflow_sysmetrics/system_context.py
mlflow_sysmetrics/utils/__init__.py
mlflow_sysmetrics/utils/constants.py
mlflow_sysmetrics/utils/mac.py
mlflow_sysmetrics/utils/windows.py
mlflow_sysmetrics-0.1.3.dist-info/LICENCE
mlflow_sysmetrics-0.1.3.dist-info/METADATA
mlflow_sysmetrics-0.1.3.dist-info/WHEEL
mlflow_sysmetrics-0.1.3.dist-info/entry_points.txt
mlflow_sysmetrics-0.1.3.dist-info/RECORD
