Metadata-Version: 2.3
Name: mlflow-sysmetrics
Version: 0.1.3
Summary: An MLflow plugin that automatically logs system-level metrics (CPU, memory, disk, GPU, OS) as run tags for improved experiment observability.
Author: Hugo Carvalho
Author-email: hugodanielsilvacarvalho.hc@gmail.com
Requires-Python: >=3.9
Classifier: Programming Language :: Python :: 3
Classifier: Programming Language :: Python :: 3.9
Classifier: Programming Language :: Python :: 3.10
Classifier: Programming Language :: Python :: 3.11
Classifier: Programming Language :: Python :: 3.12
Classifier: Programming Language :: Python :: 3.13
Requires-Dist: mlflow (>2.0.1)
Requires-Dist: psutil (>=7.0.0,<8.0.0)
